rcn/__init__.py
rcn/__main__.py
rcn/profile_func/__init__.py
rcn/rcn_http/__init__.py
rcn/rcn_http/http_client.py
rcn/utils/__init__.py
tests/__init__.py
tests/http/__init__.py
tests/http/test_client.py
rcn-2.0.0.dist-info/LICENSE
rcn-2.0.0.dist-info/METADATA
rcn-2.0.0.dist-info/WHEEL
rcn-2.0.0.dist-info/top_level.txt
rcn-2.0.0.dist-info/RECORD
