Metadata-Version: 2.1
Name: rcn
Version: 2.0.0
Summary: CLI Interface for RCN
Home-page: https://github.com/mayank31313/rcn-cli
Author: Mayank Shinde
Author-email: mayank31313@gmail.com
Keywords: ior,iot,network_robos,control_net
Classifier: Programming Language :: Python :: 3
Classifier: Operating System :: OS Independent
Classifier: Intended Audience :: Developers
License-File: LICENSE
